setup.py
distributions_load_analyze/Binomialdistribution.py
distributions_load_analyze/Gaussiandistribution.py
distributions_load_analyze/Generaldistribution.py
distributions_load_analyze/__init__.py
distributions_load_analyze.egg-info/PKG-INFO
distributions_load_analyze.egg-info/SOURCES.txt
distributions_load_analyze.egg-info/dependency_links.txt
distributions_load_analyze.egg-info/not-zip-safe
distributions_load_analyze.egg-info/top_level.txt